toolbit/__init__.py
toolbit/_hidapi.cpython-37m-darwin.so
toolbit/_toolbit.cpython-37m-darwin.so
toolbit_lib-1.0.0.data/data/header/adc.h
toolbit_lib-1.0.0.data/data/header/adc_hw.h
toolbit_lib-1.0.0.data/data/header/attribute.h
toolbit_lib-1.0.0.data/data/header/chopper.h
toolbit_lib-1.0.0.data/data/header/dmm.h
toolbit_lib-1.0.0.data/data/header/gpio_hw.h
toolbit_lib-1.0.0.data/data/header/hidapi.h
toolbit_lib-1.0.0.data/data/header/i2c_hw.h
toolbit_lib-1.0.0.data/data/header/pin.h
toolbit_lib-1.0.0.data/data/header/tbi_core.h
toolbit_lib-1.0.0.data/data/header/tbi_device.h
toolbit_lib-1.0.0.data/data/header/tbi_device_manager.h
toolbit_lib-1.0.0.data/data/header/tbi_service.h
toolbit_lib-1.0.0.data/data/header/tbit.h
toolbit_lib-1.0.0.data/data/source/hid.c
toolbit_lib-1.0.0.dist-info/METADATA
toolbit_lib-1.0.0.dist-info/WHEEL
toolbit_lib-1.0.0.dist-info/top_level.txt
toolbit_lib-1.0.0.dist-info/RECORD
