Metadata-Version: 2.1
Name: toolbit-lib
Version: 1.0.0
Summary: Toolbit library
Home-page: https://github.com/toolbitorg/ToolbitSDK
Author: Junji Ohama
Author-email: junji.ohama@toolbit.org
License: UNKNOWN
Project-URL: Bug Reports, https://github.com/toolbitorg/ToolbitSDK/issues
Project-URL: Source, https://github.com/toolbitorg/ToolbitSDK
Keywords: toolbit sdk library
Platform: UNKNOWN
Classifier: Development Status :: 4 - Beta
Classifier: Intended Audience :: Developers
Classifier: Topic :: Software Development :: Libraries :: Python Modules
Classifier: License :: OSI Approved :: GNU General Public License v2 (GPLv2)
Classifier: Programming Language :: Python :: 3
Classifier: Programming Language :: Python :: 3.6
Classifier: Programming Language :: Python :: 3.7
Classifier: Programming Language :: Python :: 3.8
Requires-Python: >=3.6
